thirdeyerepo/__init__.py
thirdeyerepo/hello.py
thirdeyerepo-0.1.0.dist-info/METADATA
thirdeyerepo-0.1.0.dist-info/WHEEL
thirdeyerepo-0.1.0.dist-info/top_level.txt
thirdeyerepo-0.1.0.dist-info/RECORD
