Metadata-Version: 2.1
Name: thirdeyerepo
Version: 0.1.0
Summary: Test
Home-page: https://github.com/allestech/thirdeyerepo
Author: Jack Ma
Author-email: jackma98004@gmail.com
Classifier: Programming Language :: Python :: 3
Classifier: License :: OSI Approved :: MIT License
Classifier: Operating System :: OS Independent
Requires-Python: >=3.6
Requires-Dist: requests >=2.20
